lexer.py
simple_shell_parser-0.1.3.dist-info/DESCRIPTION.rst
simple_shell_parser-0.1.3.dist-info/METADATA
simple_shell_parser-0.1.3.dist-info/RECORD
simple_shell_parser-0.1.3.dist-info/WHEEL
simple_shell_parser-0.1.3.dist-info/metadata.json
simple_shell_parser-0.1.3.dist-info/top_level.txt
